filelibrary/__init__.py
filelibrary/main.py
filesystem/__init__.py
filesystem/main.py
filelibrary-0.0.2.dist-info/LICENSE
filelibrary-0.0.2.dist-info/METADATA
filelibrary-0.0.2.dist-info/WHEEL
filelibrary-0.0.2.dist-info/top_level.txt
filelibrary-0.0.2.dist-info/RECORD
