Metadata-Version: 2.1
Name: filelibrary
Version: 0.0.2
Summary: filelibrary is a simple package that allows you to get and edit files or directories in a specified path.
Home-page: https://github.com/CantCode023/filesystem
Author: CantCode
Author-email: cantcode023@gmail.com
License: UNKNOWN
Platform: UNKNOWN
Classifier: Programming Language :: Python :: 3
Requires-Python: >=3.7
License-File: LICENSE
